{"expires":1784146201,"data":{"origen":"SERVIDOR REAL (LICONSA)","data":{"id_lecheria":2011008700,"nombre":"SOLEDAD ETLA","id_ruta":4,"nombre_ruta":"SAN LORENZO CACAOTEPEC","calle":"CONSTITUCION S\/N","colonia":"CENTRO","referencia":"ENTRE LA CALLE FRANCISCO I. MADERO Y CALLE MIGUEL HIDALGO","codigo_postal":"68250","latitud":17.171383,"longitud":-96.82067,"tipo_venta":"LIQUIDA","total_beneficiarios":480,"total_familias":237,"ninos":197,"adultos_mayores":137,"madres_gestacion":2,"madres_lactancia":1,"enfermedades_cronicas":2,"adolescentes":71,"mujeres_45_59":70,"nivel_marginacion":4,"promotor_id":3571,"promotor_nombre":"CUEVAS JUAREZ VERONICA","concesionario":201512,"almacen":"No asignado","telefono":"No disponible","horario_inicio":"06:00","horario_fin":"06:15","promotor":"CUEVAS JUAREZ VERONICA","concesionario_texto":"201512","nivel_marginacion_texto":"Alto","horario_atencion":"06:00 - 06:15"},"cache":false}}