{"expires":1784136060,"data":{"origen":"SERVIDOR REAL (LICONSA)","data":{"id_lecheria":2022010200,"nombre":"SAN JUAN TEPEUXILA","id_ruta":101,"nombre_ruta":"RUTA 1 Z1","calle":"INDEPENDENCIA S\/N","colonia":"CENTRO","latitud":17.723152,"longitud":-96.840701,"tipo_venta":"POLVO","promotor_id":3079,"total_beneficiarios":0,"total_familias":53,"total_ninos":96,"total_adultos_mayores":0,"precio_producto":0,"promotor":"3079","encargado":"No asignado","telefono":"No disponible","horario_inicio":"08:00","horario_fin":"14:00","referencia":"","codigo_postal":"","horario_atencion":"08:00 - 14:00"},"cache":false}}